[{"date": "5/9/26 7:35 AM ET", "teamName": "A Pete Crow-Armstrong Looked at Me", "teamId": 6, "effective": "5/9/26", "players": [{"name": "Rhett Lowder", "pos": "SP", "mlbTeam": "CIN", "action": "Dropped"}]}, {"date": "5/9/26 2:33 AM ET", "teamName": "A Pete Crow-Armstrong Looked at Me", "teamId": 6, "effective": "5/9/26", "players": [{"name": "Brent Headrick", "pos": "RP", "mlbTeam": "NYY", "action": "Added off Waivers"}]}, {"date": "5/8/26 7:49 AM ET", "teamName": "A Pete Crow-Armstrong Looked at Me", "teamId": 6, "effective": "5/8/26", "players": [{"name": "Andres Gimenez", "pos": "2B,SS", "mlbTeam": "TOR", "action": "Dropped"}]}, {"date": "5/8/26 5:34 AM ET", "teamName": "A Pete Crow-Armstrong Looked at Me", "teamId": 6, "effective": "5/8/26", "players": [{"name": "Nate Lowe", "pos": "1B", "mlbTeam": "CIN", "action": "Added off Waivers"}, {"name": "Matthew Boyd", "pos": "SP", "mlbTeam": "CHC", "action": "Dropped"}]}, {"date": "5/7/26 2:33 AM ET", "teamName": "A Pete Crow-Armstrong Looked at Me", "teamId": 6, "effective": "5/7/26", "players": [{"name": "Sean Burke", "pos": "SP", "mlbTeam": "CHW", "action": "Added off Waivers"}, {"name": "Noah Cameron", "pos": "SP", "mlbTeam": "KC", "action": "Dropped"}]}, {"date": "5/2/26 7:58 AM ET", "teamName": "A Pete Crow-Armstrong Looked at Me", "teamId": 6, "effective": "5/2/26", "players": [{"name": "Jacob Latz", "pos": "SP,RP", "mlbTeam": "TEX", "action": "Activated"}]}, {"date": "5/2/26 7:58 AM ET", "teamName": "A Pete Crow-Armstrong Looked at Me", "teamId": 6, "effective": "5/2/26", "players": [{"name": "Jacob Latz", "pos": "SP,RP", "mlbTeam": "TEX", "action": "Added off Waivers"}, {"name": "Hunter Gaddis", "pos": "RP", "mlbTeam": "CLE", "action": "Dropped"}]}, {"date": "4/29/26 3:03 AM ET", "teamName": "A Pete Crow-Armstrong Looked at Me", "teamId": 6, "effective": "4/29/26", "players": [{"name": "Spencer Arrighetti", "pos": "SP", "mlbTeam": "HOU", "action": "Activated"}]}, {"date": "4/29/26 3:03 AM ET", "teamName": "A Pete Crow-Armstrong Looked at Me", "teamId": 6, "effective": "4/29/26", "players": [{"name": "Spencer Arrighetti", "pos": "SP", "mlbTeam": "HOU", "action": "Added off Waivers"}, {"name": "Luis Castillo", "pos": "SP", "mlbTeam": "SEA", "action": "Dropped"}]}, {"date": "4/24/26 1:44 AM ET", "teamName": "A Pete Crow-Armstrong Looked at Me", "teamId": 6, "effective": "4/24/26", "players": [{"name": "Justin Wrobleski", "pos": "SP,RP", "mlbTeam": "LAD", "action": "Added off Waivers"}, {"name": "Spencer Arrighetti", "pos": "SP", "mlbTeam": "HOU", "action": "Dropped"}]}, {"date": "4/24/26 1:44 AM ET", "teamName": "A Pete Crow-Armstrong Looked at Me", "teamId": 6, "effective": "4/24/26", "players": [{"name": "Enyel De Los Santos", "pos": "RP", "mlbTeam": "HOU", "action": "Activated"}]}, {"date": "4/24/26 1:44 AM ET", "teamName": "A Pete Crow-Armstrong Looked at Me", "teamId": 6, "effective": "4/24/26", "players": [{"name": "Enyel De Los Santos", "pos": "RP", "mlbTeam": "HOU", "action": "Added off Waivers"}, {"name": "Bryan King", "pos": "RP", "mlbTeam": "HOU", "action": "Dropped"}]}, {"date": "4/21/26 2:15 AM ET", "teamName": "A Pete Crow-Armstrong Looked at Me", "teamId": 6, "effective": "4/21/26", "players": [{"name": "Tyler Alexander", "pos": "SP,RP", "mlbTeam": "TEX", "action": "Added off Waivers"}, {"name": "Aaron Civale", "pos": "SP", "mlbTeam": "ATH", "action": "Dropped"}]}, {"date": "4/21/26 2:15 AM ET", "teamName": "A Pete Crow-Armstrong Looked at Me", "teamId": 6, "effective": "4/21/26", "players": [{"name": "Andres Gimenez", "pos": "2B,SS", "mlbTeam": "TOR", "action": "Added off Waivers"}, {"name": "Kerry Carpenter", "pos": "LF,RF", "mlbTeam": "DET", "action": "Dropped"}]}, {"date": "4/21/26 2:15 AM ET", "teamName": "A Pete Crow-Armstrong Looked at Me", "teamId": 6, "effective": "4/21/26", "players": [{"name": "Spencer Arrighetti", "pos": "SP", "mlbTeam": "HOU", "action": "Added off Waivers"}, {"name": "Andrew Abbott", "pos": "SP", "mlbTeam": "CIN", "action": "Dropped"}]}, {"date": "4/21/26 2:15 AM ET", "teamName": "A Pete Crow-Armstrong Looked at Me", "teamId": 6, "effective": "4/21/26", "players": [{"name": "Blake Treinen", "pos": "RP", "mlbTeam": "LAD", "action": "Added off Waivers"}, {"name": "Corbin Burnes", "pos": "SP", "mlbTeam": "ARI", "action": "Dropped"}]}, {"date": "4/17/26 1:45 AM ET", "teamName": "A Pete Crow-Armstrong Looked at Me", "teamId": 6, "effective": "4/17/26", "players": [{"name": "Aaron Civale", "pos": "SP", "mlbTeam": "ATH", "action": "Added off Waivers"}, {"name": "Tyler Mahle", "pos": "SP", "mlbTeam": "SF", "action": "Dropped"}]}, {"date": "4/14/26 3:10 AM ET", "teamName": "A Pete Crow-Armstrong Looked at Me", "teamId": 6, "effective": "4/14/26", "players": [{"name": "Jeffrey Springs", "pos": "SP", "mlbTeam": "ATH", "action": "Added off Waivers"}, {"name": "Hunter Harvey", "pos": "RP", "mlbTeam": "CHC", "action": "Dropped"}]}, {"date": "4/10/26 3:09 AM ET", "teamName": "A Pete Crow-Armstrong Looked at Me", "teamId": 6, "effective": "4/10/26", "players": [{"name": "Joey Cantillo", "pos": "SP,RP", "mlbTeam": "CLE", "action": "Added off Waivers"}, {"name": "Shane Smith", "pos": "SP", "mlbTeam": "CHW", "action": "Dropped"}]}, {"date": "4/7/26 2:07 AM ET", "teamName": "A Pete Crow-Armstrong Looked at Me", "teamId": 6, "effective": "4/7/26", "players": [{"name": "Seth Lugo", "pos": "SP", "mlbTeam": "KC", "action": "Added off Waivers"}, {"name": "Jesus Sanchez", "pos": "LF,RF", "mlbTeam": "TOR", "action": "Dropped"}]}, {"date": "4/5/26 1:48 AM ET", "teamName": "A Pete Crow-Armstrong Looked at Me", "teamId": 6, "effective": "4/5/26", "players": [{"name": "Jesus Sanchez", "pos": "LF,RF", "mlbTeam": "TOR", "action": "Added off Waivers"}]}, {"date": "3/26/26 7:32 AM ET", "teamName": "A Pete Crow-Armstrong Looked at Me", "teamId": 6, "effective": "3/26/26", "players": [{"name": "Tyler Mahle", "pos": "SP", "mlbTeam": "SF", "action": "Added"}]}, {"date": "3/24/26 12:34 PM ET", "teamName": "A Pete Crow-Armstrong Looked at Me", "teamId": 6, "effective": "3/25/26", "players": [{"name": "Bryan King", "pos": "RP", "mlbTeam": "HOU", "action": "Added"}]}, {"date": "3/19/26 7:25 AM ET", "teamName": "A Pete Crow-Armstrong Looked at Me", "teamId": 6, "effective": "3/25/26", "players": [{"name": "Max Meyer", "pos": "SP", "mlbTeam": "MIA", "action": "Dropped"}]}, {"date": "3/19/26 7:24 AM ET", "teamName": "A Pete Crow-Armstrong Looked at Me", "teamId": 6, "effective": "3/25/26", "players": [{"name": "Giancarlo Stanton", "pos": "DH", "mlbTeam": "NYY", "action": "Dropped"}]}, {"date": "3/19/26 7:24 AM ET", "teamName": "A Pete Crow-Armstrong Looked at Me", "teamId": 6, "effective": "3/25/26", "players": [{"name": "Tyler Stephenson", "pos": "C", "mlbTeam": "CIN", "action": "Dropped"}]}, {"date": "3/19/26 7:23 AM ET", "teamName": "A Pete Crow-Armstrong Looked at Me", "teamId": 6, "effective": "3/25/26", "players": [{"name": "Spencer Arrighetti", "pos": "SP", "mlbTeam": "HOU", "action": "Dropped"}]}]