{
  "completedAt": "2026-04-26T13:26:56.810412Z",
  "phaseA": {
    "stats": "ok",
    "injuries": "ok",
    "news": "ok"
  },
  "phaseB": {
    "cbs_auth": "ok",
    "transactions": "ok",
    "rosters": "ok",
    "matchup": "ok"
  },
  "notes": [
    "Stats fetched from MLB Stats API (450 batters / 525 pitchers).",
    "fetch_stuffplus.py 403'd / pybaseball not installed (expected, non-fatal).",
    "Scraped 237 injuries and 50 news items from public CBS pages.",
    "CBS auth healthy; pulled 219 raw transactions from print_rows=9999 view.",
    "merge_tx cleaner consolidated 219 \u2192 182 rows.",
    "Rosters scraped via /teams/{1..12} JSON-encoded then committed.",
    "Period 2 in progress; matchup vs Dinosaur Jr Caminero, currently 9-7."
  ]
}