[
  {
    "player": "Yankees",
    "headline": "How run-it-back Yankees got off to such a hot start",
    "date": "2026-04-03"
  },
  {
    "player": "Dylan Cease",
    "headline": "Trends: Cease's new changeup, McLain's resurgence, more",
    "date": "2026-04-03"
  },
  {
    "player": "Paul Skenes",
    "headline": "Pirates ace Paul Skenes rebounds, even if he still doesn't look himself",
    "date": "2026-04-03"
  },
  {
    "player": "MLB",
    "headline": "MLB Power Rankings: What's real after five days?",
    "date": "2026-04-03"
  },
  {
    "player": "Carter Jensen",
    "headline": "Royals' Jensen scratched from lineup after sleeping through alarm",
    "date": "2026-04-03"
  },
  {
    "player": "Konnor Griffin",
    "headline": "Pirates call up top prospect Konnor Griffin for MLB debut",
    "date": "2026-04-03"
  },
  {
    "player": "Masyn Winn",
    "headline": "Cardinals shortstop Masyn Winn 'OK' after single-car accident",
    "date": "2026-04-03"
  },
  {
    "player": "Matt Chapman",
    "headline": "Frustration spills over for Giants as Chapman appears to cuss out Schmitt",
    "date": "2026-04-03"
  },
  {
    "player": "Orioles",
    "headline": "Orioles beat Rangers on game-ending ABS challenge",
    "date": "2026-04-03"
  },
  {
    "player": "Andrew Painter",
    "headline": "Andrew Painter, top Phillies prospect, impresses in long-awaited debut",
    "date": "2026-04-02"
  },
  {
    "player": "Chris Sale",
    "headline": "Chris Sale illness update - Questionable",
    "date": "2026-04-03"
  },
  {
    "player": "Shohei Ohtani",
    "headline": "Shohei Ohtani placed on IL with shoulder injury",
    "date": "2026-04-02"
  },
  {
    "player": "Jordan Lawlar",
    "headline": "Jordan Lawlar probable to return from wrist issue",
    "date": "2026-04-03"
  },
  {
    "player": "Michael Wacha",
    "headline": "Michael Wacha questionable with illness",
    "date": "2026-04-03"
  },
  {
    "player": "Jose Ramirez",
    "headline": "Jose Ramirez on IL with knee injury, expected back Apr 6",
    "date": "2026-04-02"
  }
]